<?xml version="1.0" encoding="UTF-8"?>
<objects serializationModel="Studio.02.00.00">
	<object class="AudioFile" id="{aeab71b3-7707-4cd4-9b96-a1060248ef52}">
		<property name="assetPath">
			<value>NL_season_change_spring.flac</value>
		</property>
		<property name="frequencyInKHz">
			<value>48</value>
		</property>
		<property name="channelCount">
			<value>2</value>
		</property>
		<property name="length">
			<value>3.6202708333333335</value>
		</property>
		<relationship name="masterAssetFolder">
			<destination>{c5e18e81-3898-4af6-834b-a15b3ca1f3bd}</destination>
		</relationship>
	</object>
</objects>
